shopwareapi/__init__.py
shopwareapi/client.py
shopwareapi/exceptions.py
shopwareapi/api/__init__.py
shopwareapi/api/category/__init__.py
shopwareapi/api/category/category_model.py
shopwareapi/api/cms_page/__init__.py
shopwareapi/api/cms_page/cms_page_model.py
shopwareapi/api/currency/__init__.py
shopwareapi/api/currency/currency_model.py
shopwareapi/api/media/__init__.py
shopwareapi/api/media/media_folder_configuration_model.py
shopwareapi/api/media/media_folder_model.py
shopwareapi/api/media/media_model.py
shopwareapi/api/product/__init__.py
shopwareapi/api/product/product_cross_selling_assigned_product_model.py
shopwareapi/api/product/product_cross_selling_model.py
shopwareapi/api/product/product_manufacturer_model.py
shopwareapi/api/product/product_media_model.py
shopwareapi/api/product/product_model.py
shopwareapi/api/sales_channel/__init__.py
shopwareapi/api/sales_channel/sales_channel_model.py
shopwareapi/api/tag/__init__.py
shopwareapi/api/tag/tag_model.py
shopwareapi/api/tax/__init__.py
shopwareapi/api/tax/tax_model.py
shopwareapi/api/unit/__init__.py
shopwareapi/api/unit/unit_model.py
shopwareapi/core/__init__.py
shopwareapi/core/field.py
shopwareapi/core/lazymodel.py
shopwareapi/core/manager.py
shopwareapi/core/model.py
shopwareapi/core/options.py
shopwareapi/core/query.py
shopwareapi/fields/__init__.py
shopwareapi/fields/boolean_field.py
shopwareapi/fields/char_field.py
shopwareapi/fields/dict_field.py
shopwareapi/fields/integer_field.py
shopwareapi/fields/list_field.py
shopwareapi/fields/number_field.py
shopwareapi/fields/relation_field.py
shopwareapi/fields/uuid_field.py
shopwareapi/utils/__init__.py
shopwareapi/utils/auth.py
shopwareapi/utils/conf.py
shopwareapi/utils/helper.py
shopwareapi/utils/http.py
shopwareapi/utils/lazy.py
tests/__init__.py
tests/test_core_model.py
tests/test_utils_auth.py
tests/test_utils_conf.py
tests/test_utils_http.py
tests/tests_client.py
shopwareapi-0.1.26.dist-info/METADATA
shopwareapi-0.1.26.dist-info/WHEEL
shopwareapi-0.1.26.dist-info/top_level.txt
shopwareapi-0.1.26.dist-info/RECORD
