Metadata-Version: 2.1
Name: shopwareapi
Version: 0.1.26
Summary: Provides a Python (object-based) API for Shopware
Home-page: https://github.com/Sachs-Media/shopwareapi
Author: Stefan Eiermann, Sachs Media
Author-email: support@sachs-media.com
License: UNKNOWN
Platform: UNKNOWN
Classifier: Programming Language :: Python :: 3
Classifier: License :: OSI Approved :: MIT License
Classifier: Operating System :: OS Independent
Classifier: Topic :: Office/Business
Classifier: Topic :: Utilities
Classifier: Topic :: Software Development :: Libraries
Requires-Python: >=3.6
Requires-Dist: requests (>=2.25.0)
